aiovodafone/__init__.py
aiovodafone/api.py
aiovodafone/const.py
aiovodafone/exceptions.py
aiovodafone/models/__init__.py
aiovodafone/models/sercomm.py
aiovodafone/models/technicolor.py
aiovodafone/models/ultrahub.py
aiovodafone/py.typed
aiovodafone/sjcl.py
aiovodafone-3.1.1.dist-info/METADATA
aiovodafone-3.1.1.dist-info/WHEEL
aiovodafone-3.1.1.dist-info/licenses/LICENSE
aiovodafone-3.1.1.dist-info/RECORD
