Metadata-Version: 2.4
Name: aiovodafone
Version: 3.1.1
Summary: Python library to control Vodafone Station
License-Expression: Apache-2.0
License-File: LICENSE
Author: Simone Chemelli
Author-email: simone.chemelli@gmail.com
Requires-Python: >=3.12
Classifier: Development Status :: 5 - Production/Stable
Classifier: Intended Audience :: Developers
Classifier: Natural Language :: English
Classifier: Operating System :: OS Independent
Classifier: Topic :: Software Development :: Libraries
Requires-Dist: aiohttp (>=3.12.7)
Requires-Dist: beautifulsoup4
Requires-Dist: colorlog
Requires-Dist: cryptography (>=45.0.3)
Requires-Dist: orjson (>=3.10,<4)
Requires-Dist: pycryptodome (>=3.17,<4)
Requires-Dist: segno (>=1.6.6)
Project-URL: Bug Tracker, https://github.com/chemelli74/aiovodafone/issues
Project-URL: Changelog, https://github.com/chemelli74/aiovodafone/blob/main/CHANGELOG.md
Project-URL: Homepage, https://github.com/chemelli74/aiovodafone
